logging_arg_count.py
flake8_logging_arg_count-0.4.1.dist-info/licenses/LICENSE
flake8_logging_arg_count-0.4.1.dist-info/METADATA
flake8_logging_arg_count-0.4.1.dist-info/WHEEL
flake8_logging_arg_count-0.4.1.dist-info/entry_points.txt
flake8_logging_arg_count-0.4.1.dist-info/top_level.txt
flake8_logging_arg_count-0.4.1.dist-info/RECORD
