Metadata-Version: 2.4
Name: flake8-logging-arg-count
Version: 0.4.1
Summary: A flake8 plugin for detecting logging statements with mismatched argument counts
License: Apache License Version 2.0
Project-URL: github, https://github.com/samety/flake8-logging-arg-count
Keywords: flake8,flake8.plugin,flake8.extension
Classifier: Programming Language :: Python :: 3
Classifier: Programming Language :: Python :: 3 :: Only
Classifier: License :: OSI Approved :: Apache Software License
Requires-Python: >=3.9
License-File: LICENSE
Dynamic: license-file
